pngrok/__init__.py
pngrok/client.py
pngrok/pngrok.py
pngrok/server.py
pngrok_jawide-0.0.3.dist-info/LICENSE
pngrok_jawide-0.0.3.dist-info/METADATA
pngrok_jawide-0.0.3.dist-info/WHEEL
pngrok_jawide-0.0.3.dist-info/top_level.txt
pngrok_jawide-0.0.3.dist-info/RECORD
