Metadata-Version: 2.1
Name: pngrok-jawide
Version: 0.0.3
Summary: 这是一个使用python实现的内网穿透服务，完全使用标准库实现
Home-page: https://gitee.com/jawide/pngrok
Author: jawide
Author-email: jawide@qq.com
License: UNKNOWN
Platform: UNKNOWN
Classifier: Programming Language :: Python :: 3
Classifier: License :: OSI Approved :: MIT License
Classifier: Operating System :: OS Independent
